pydantic_pkgr-0.5.4.dist-info/METADATA
pydantic_pkgr-0.5.4.dist-info/WHEEL
pydantic_pkgr-0.5.4.dist-info/entry_points.txt
pydantic_pkgr-0.5.4.dist-info/licenses/LICENSE
pydantic_pkgr/.DS_Store
pydantic_pkgr/__init__.py
pydantic_pkgr/admin.py
pydantic_pkgr/apps.py
pydantic_pkgr/base_types.py
pydantic_pkgr/binary.py
pydantic_pkgr/binprovider.py
pydantic_pkgr/binprovider_ansible.py
pydantic_pkgr/binprovider_apt.py
pydantic_pkgr/binprovider_brew.py
pydantic_pkgr/binprovider_npm.py
pydantic_pkgr/binprovider_pip.py
pydantic_pkgr/binprovider_pyinfra.py
pydantic_pkgr/models.py
pydantic_pkgr/semver.py
pydantic_pkgr/settings.py
pydantic_pkgr/shallowbinary.py
pydantic_pkgr/tests.py
pydantic_pkgr/views.py
pydantic_pkgr-0.5.4.dist-info/RECORD
