Metadata-Version: 2.1
Name: pydantic-pkgr
Version: 0.5.4
Summary: System package manager APIs in strongly typed Python
Keywords: pydantic,packagemanager,apt,brew,pip,system,dependencies
Author-Email: Nick Sweeting <pydantic-pkgr-pyproject-toml@sweeting.me>
License: MIT
Classifier: Programming Language :: Python
Classifier: Programming Language :: Python :: 3
Classifier: Programming Language :: Python :: 3 :: Only
Classifier: Programming Language :: Python :: 3.10
Classifier: Programming Language :: Python :: 3.11
Classifier: Programming Language :: Python :: 3.12
Classifier: Framework :: Django
Classifier: Framework :: Django :: 4.0
Classifier: Framework :: Django :: 4.1
Classifier: Framework :: Django :: 4.2
Classifier: Framework :: Django :: 5.0
Classifier: Framework :: Django :: 5.1
Classifier: Environment :: Web Environment
Classifier: Intended Audience :: Developers
Classifier: Natural Language :: English
Project-URL: Homepage, https://github.com/ArchiveBox/pydantic-pkgr
Project-URL: Source, https://github.com/ArchiveBox/pydantic-pkgr
Project-URL: Documentation, https://github.com/ArchiveBox/pydantic-pkgr
Project-URL: Bug tracker, https://github.com/ArchiveBox/pydantic-pkgr/issues
Project-URL: Changelog, https://github.com/ArchiveBox/pydantic-pkgr/releases
Project-URL: Donate, https://github.com/ArchiveBox/ArchiveBox/wiki/Donations
Requires-Python: >=3.10
Requires-Dist: typing-extensions>=4.11.0
Requires-Dist: platformdirs>=4.3.6
Requires-Dist: pydantic>=2.7.1
Requires-Dist: pydantic-core>=2.18.2
Provides-Extra: pyinfra
Requires-Dist: pyinfra>=2.6.1; extra == "pyinfra"
Provides-Extra: ansible
Requires-Dist: ansible; extra == "ansible"
Requires-Dist: ansible-core; extra == "ansible"
Requires-Dist: ansible-runner; extra == "ansible"
Provides-Extra: all
Requires-Dist: pydantic-pkgr[ansible,pyinfra]; extra == "all"
